{"$schema": "https://ui.shadcn.com/schema/registry-item.json", "name": "footer-06", "description": "A simple footer.", "dependencies": ["@aliimam/logos"], "files": [{"path": "blocks/footer/footer-06/footer.tsx", "content": "import { Apple, Github, LinkedIn, X } from \"@aliimam/logos\"\n\nexport default function Footer() {\n  return (\n    <div className=\"flex h-screen w-full flex-col items-center justify-center\">\n      <div className=\"container flex h-auto flex-col items-stretch justify-between self-stretch md:flex-row\">\n        <div className=\"flex h-auto flex-col items-start justify-start gap-8 p-4 md:p-8\">\n          <div className=\"flex items-center justify-start gap-3 self-stretch\">\n            <div className=\"text-center text-xl leading-4 font-semibold\">\n              <Apple className=\"text-primary\" />\n            </div>\n          </div>\n          <div className=\"text-sm font-medium\">\n            <h1 className=\"text-lg font-medium\">Design without limits</h1>\n            <p className=\"text-muted-foreground max-w-md\">\n              I create digital experiences that connect and inspire. I build\n              apps, websites, brands, and products end-to-end.\n            </p>\n          </div>\n\n          <div className=\"flex items-start justify-start gap-6\">\n            <LinkedIn className=\"w-6\" />\n            <X className=\"w-6\" />\n            <Github className=\"w-6\" />\n          </div>\n        </div>\n\n        <div className=\"flex flex-col flex-wrap items-start justify-start gap-6 self-stretch p-4 sm:flex-row sm:justify-between md:gap-8 md:p-8\">\n          <div className=\"flex min-w-40 flex-1 flex-col items-start justify-start gap-3\">\n            <div className=\"self-stretch text-sm leading-5 font-medium\">\n              Product\n            </div>\n            <div className=\"flex flex-col items-start justify-end gap-2\">\n              <div className=\"text-muted-foreground hover:text-primary cursor-pointer text-sm leading-5 font-normal transition-colors\">\n                Features\n              </div>\n              <div className=\"text-muted-foreground hover:text-primary cursor-pointer text-sm leading-5 font-normal transition-colors\">\n                Pricing\n              </div>\n              <div className=\"text-muted-foreground hover:text-primary cursor-pointer text-sm leading-5 font-normal transition-colors\">\n                Integrations\n              </div>\n              <div className=\"text-muted-foreground hover:text-primary cursor-pointer text-sm leading-5 font-normal transition-colors\">\n                Real-time Previews\n              </div>\n              <div className=\"text-muted-foreground hover:text-primary cursor-pointer text-sm leading-5 font-normal transition-colors\">\n                Multi-Agent Coding\n              </div>\n            </div>\n          </div>\n\n          <div className=\"flex min-w-40 flex-1 flex-col items-start justify-start gap-3\">\n            <div className=\"text-sm leading-5 font-medium\">Company</div>\n            <div className=\"flex flex-col items-start justify-center gap-2\">\n              <div className=\"text-muted-foreground hover:text-primary cursor-pointer text-sm leading-5 font-normal transition-colors\">\n                About us\n              </div>\n              <div className=\"text-muted-foreground hover:text-primary cursor-pointer text-sm leading-5 font-normal transition-colors\">\n                Our team\n              </div>\n              <div className=\"text-muted-foreground hover:text-primary cursor-pointer text-sm leading-5 font-normal transition-colors\">\n                Careers\n              </div>\n              <div className=\"text-muted-foreground hover:text-primary cursor-pointer text-sm leading-5 font-normal transition-colors\">\n                Brand\n              </div>\n              <div className=\"text-muted-foreground hover:text-primary cursor-pointer text-sm leading-5 font-normal transition-colors\">\n                Contact\n              </div>\n            </div>\n          </div>\n\n          <div className=\"flex min-w-40 flex-1 flex-col items-start justify-start gap-3\">\n            <div className=\"text-sm leading-5 font-medium\">Resources</div>\n            <div className=\"flex flex-col items-center justify-center gap-2\">\n              <div className=\"text-muted-foreground hover:text-primary cursor-pointer self-stretch text-sm leading-5 font-normal transition-colors\">\n                Terms of use\n              </div>\n              <div className=\"text-muted-foreground hover:text-primary cursor-pointer self-stretch text-sm leading-5 font-normal transition-colors\">\n                API Reference\n              </div>\n              <div className=\"text-muted-foreground hover:text-primary cursor-pointer self-stretch text-sm leading-5 font-normal transition-colors\">\n                Documentation\n              </div>\n              <div className=\"text-muted-foreground hover:text-primary cursor-pointer self-stretch text-sm leading-5 font-normal transition-colors\">\n                Community\n              </div>\n              <div className=\"text-muted-foreground hover:text-primary cursor-pointer self-stretch text-sm leading-5 font-normal transition-colors\">\n                Support\n              </div>\n            </div>\n          </div>\n        </div>\n      </div>\n\n      <div className=\"relative h-12 self-stretch overflow-hidden border-t border-b\">\n        <div className=\"absolute inset-0 h-full w-full overflow-hidden\">\n          <div className=\"relative h-full w-full\">\n            {Array.from({ length: 300 }).map((_, i) => (\n              <div\n                key={i}\n                className=\"outline-primary/40 absolute h-4 w-full origin-top-left -rotate-45 outline-[0.5px] outline-offset-[-0.25px]\"\n                style={{\n                  top: `${i * 16 - 120}px`,\n                  left: \"-100%\",\n                  width: \"300%\",\n                }}\n              ></div>\n            ))}\n          </div>\n        </div>\n      </div>\n    </div>\n  )\n}\n", "type": "registry:component", "target": "layout/footer/index.tsx"}], "meta": {"iframeHeight": "600px"}, "categories": ["footer"], "type": "registry:block"}