{"$schema": "https://ui.shadcn.com/schema/registry-item.json", "name": "breadcrumb-nav", "title": "Breadcrumb Nav", "files": [{"path": "src/components/thegridcn/breadcrumb-nav.tsx", "content": "\"use client\"\n\nimport * as React from \"react\"\nimport { cn } from \"@/lib/utils\"\n\ninterface BreadcrumbItem {\n  label: string\n  href?: string\n  active?: boolean\n}\n\ninterface BreadcrumbNavProps extends React.HTMLAttributes<HTMLElement> {\n  items: BreadcrumbItem[]\n  separator?: \"chevron\" | \"slash\" | \"dot\"\n}\n\nfunction SeparatorIcon({ type }: { type: string }) {\n  if (type === \"slash\") {\n    return <span className=\"text-foreground/20 font-mono text-[10px]\">/</span>\n  }\n  if (type === \"dot\") {\n    return <span className=\"h-1 w-1 rounded-full bg-foreground/20\" />\n  }\n  // chevron\n  return (\n    <svg width=\"10\" height=\"10\" viewBox=\"0 0 10 10\" fill=\"none\" className=\"text-foreground/20\">\n      <path d=\"M3.5 2l3.5 3-3.5 3\" stroke=\"currentColor\" strokeWidth=\"1.2\" strokeLinecap=\"round\" strokeLinejoin=\"round\" />\n    </svg>\n  )\n}\n\nexport function BreadcrumbNav({\n  items,\n  separator = \"chevron\",\n  className,\n  ...props\n}: BreadcrumbNavProps) {\n  return (\n    <nav\n      data-slot=\"tron-breadcrumb\"\n      aria-label=\"Breadcrumb\"\n      className={cn(\n        \"inline-flex items-center gap-2 rounded border border-primary/20 bg-card/80 px-3 py-1.5 backdrop-blur-sm\",\n        className\n      )}\n      {...props}\n    >\n      {items.map((item, i) => (\n        <React.Fragment key={i}>\n          {i > 0 && (\n            <span className=\"flex items-center\">\n              <SeparatorIcon type={separator} />\n            </span>\n          )}\n          {item.active ? (\n            <span className=\"font-mono text-[10px] uppercase tracking-widest text-primary\">\n              {item.label}\n            </span>\n          ) : item.href ? (\n            <a\n              href={item.href}\n              className=\"font-mono text-[10px] uppercase tracking-widest text-foreground/40 transition-colors hover:text-primary\"\n            >\n              {item.label}\n            </a>\n          ) : (\n            <span className=\"font-mono text-[10px] uppercase tracking-widest text-foreground/40\">\n              {item.label}\n            </span>\n          )}\n        </React.Fragment>\n      ))}\n    </nav>\n  )\n}\n", "type": "registry:component"}], "type": "registry:component"}