{"$schema": "https://ui.shadcn.com/schema/registry-item.json", "name": "social-proof3", "type": "registry:block", "title": "8-bit Social Proof 3", "description": "Swipeable review carousel with ratings.", "categories": ["social-proof"], "registryDependencies": ["badge", "card", "carousel"], "files": [{"path": "components/ui/8bit/blocks/social-proof3.tsx", "type": "registry:block", "target": "components/ui/8bit/blocks/social-proof3.tsx", "content": "\"use client\";\n\nimport { cn } from \"@/lib/utils\";\n\nimport { Badge } from \"@/components/ui/8bit/badge\";\nimport {\n  Card,\n  CardContent,\n} from \"@/components/ui/8bit/card\";\nimport {\n  Carousel,\n  CarouselContent,\n  CarouselItem,\n  CarouselNext,\n  CarouselPrevious,\n} from \"@/components/ui/8bit/carousel\";\n\nimport \"@/components/ui/8bit/styles/retro.css\";\n\nexport interface Review {\n  badge?: string;\n  name: string;\n  quote: string;\n  rating: number;\n  role: string;\n}\n\ninterface SocialProof3Props {\n  className?: string;\n  description?: string;\n  items?: Review[];\n  title?: string;\n}\n\nfunction StarRating({ rating }: { rating: number }) {\n  return (\n    <span className=\"retro text-[10px]\">\n      {\"[*]\".repeat(rating)}\n      {\"[.]\".repeat(5 - rating)}\n    </span>\n  );\n}\n\nconst defaultItems: Review[] = [\n  {\n    name: \"SwordSmith\",\n    role: \"Founder\",\n    quote: \"Replaced our entire component library in a weekend. Customers love the retro feel.\",\n    rating: 5,\n  },\n  {\n    name: \"ArcadePro\",\n    role: \"Frontend Dev\",\n    quote: \"The carousel and accordion components are rock solid. Zero accessibility issues.\",\n    rating: 5,\n    badge: \"POWER USER\",\n  },\n  {\n    name: \"NeonByte\",\n    role: \"Solo Dev\",\n    quote: \"I was skeptical about pixel borders in production. My bounce rate dropped 40%.\",\n    rating: 4,\n  },\n  {\n    name: \"QuestRunner\",\n    role: \"Agency Owner\",\n    quote: \"We use this for all our gaming clients. Saves us weeks of custom work.\",\n    rating: 5,\n  },\n  {\n    name: \"GlitchHero\",\n    role: \"Open Source\",\n    quote: \"Great DX. The docs are clear and components just work. Contributed my first PR in 10 minutes.\",\n    rating: 5,\n    badge: \"CONTRIBUTOR\",\n  },\n];\n\nexport default function SocialProof3({\n  title = \"Player Reviews\",\n  description = \"Real feedback from the community\",\n  items = defaultItems,\n  className,\n}: SocialProof3Props) {\n  return (\n    <section className={cn(\"w-full px-4 py-16\", className)}>\n      <div className=\"mx-auto max-w-4xl\">\n        {(title || description) && (\n          <div className=\"mb-10 text-center\">\n            {title && (\n              <h2 className=\"retro mb-3 font-bold text-2xl tracking-tight md:text-3xl\">\n                {title}\n              </h2>\n            )}\n            {description && (\n              <p className=\"retro text-muted-foreground text-[9px]\">{description}</p>\n            )}\n          </div>\n        )}\n\n        <Carousel\n          className=\"mx-auto w-full max-w-3xl\"\n          opts={{ align: \"start\", loop: true }}\n        >\n          <CarouselContent>\n            {items.map((item) => (\n              <CarouselItem\n                className=\"sm:basis-1/2\"\n                key={item.name}\n              >\n                <div className=\"h-full p-2\">\n                  <Card className=\"relative h-full\">\n                    {item.badge && (\n                      <div className=\"absolute top-2 right-4 z-10\">\n                        <Badge className=\"text-[9px]\">{item.badge}</Badge>\n                      </div>\n                    )}\n                    <CardContent className=\"flex h-full flex-col pt-6\">\n                      <StarRating rating={item.rating} />\n                      <p className=\"mt-3 flex-1 retro text-[9px] leading-relaxed\">\n                        &quot;{item.quote}&quot;\n                      </p>\n                      <div className=\"mt-4\">\n                        <span className=\"retro font-bold text-[10px]\">\n                          {item.name}\n                        </span>\n                        <span className=\"retro text-muted-foreground text-[10px]\">\n                          {\" \"}/ {item.role}\n                        </span>\n                      </div>\n                    </CardContent>\n                  </Card>\n                </div>\n              </CarouselItem>\n            ))}\n          </CarouselContent>\n          <CarouselPrevious />\n          <CarouselNext />\n        </Carousel>\n      </div>\n    </section>\n  );\n}\n"}, {"path": "components/ui/8bit/styles/retro.css", "type": "registry:file", "target": "components/ui/8bit/styles/retro.css", "content": "@import url(\"https://fonts.googleapis.com/css2?family=Press+Start+2P&display=swap\");\n\n.retro {\n  font-family:\n    \"Press Start 2P\",\n    system-ui,\n    -apple-system,\n    sans-serif;\n  line-height: 1.5;\n  letter-spacing: 0.5px;\n}\n\n.pixelated {\n  image-rendering: pixelated;\n  image-rendering: crisp-edges;\n}"}, {"path": "components/ui/8bit/badge.tsx", "type": "registry:component", "content": "import { type VariantProps, cva } from \"class-variance-authority\";\n\nimport { cn } from \"@/lib/utils\";\n\nimport { Badge as ShadcnBadge } from \"@/components/ui/badge\";\n\nexport const badgeVariants = cva(\"\", {\n  variants: {\n    font: {\n      normal: \"\",\n      retro: \"retro\",\n    },\n    variant: {\n      default: \"border-primary bg-primary\",\n      destructive: \"border-destructive bg-destructive\",\n      outline: \"border-background bg-background\",\n      secondary: \"border-secondary bg-secondary\",\n    },\n  },\n  defaultVariants: {\n    variant: \"default\",\n  },\n});\n\nexport interface BitButtonProps\n  extends React.ButtonHTMLAttributes<HTMLButtonElement>,\n    VariantProps<typeof badgeVariants> {\n  asChild?: boolean;\n}\n\nfunction Badge({\n  children,\n  className = \"\",\n  font,\n  variant,\n  ...props\n}: BitButtonProps) {\n  const color = badgeVariants({ variant, font });\n\n  const classes = className.split(\" \");\n\n  // visual classes for badge and sidebars\n  const visualClasses = classes.filter(\n    (c) =>\n      c.startsWith(\"bg-\") ||\n      c.startsWith(\"border-\") ||\n      c.startsWith(\"text-\") ||\n      c.startsWith(\"rounded-\")\n  );\n\n  // Container should accept all non-visual utility classes (e.g., size, spacing, layout)\n  const containerClasses = classes.filter(\n    (c) =>\n      !(\n        c.startsWith(\"bg-\") ||\n        c.startsWith(\"border-\") ||\n        c.startsWith(\"text-\") ||\n        c.startsWith(\"rounded-\")\n      )\n  );\n\n  return (\n    <div className={cn(\"relative inline-flex items-stretch\", containerClasses)}>\n      <ShadcnBadge\n        {...props}\n        className={cn(\n          \"h-full\",\n          \"rounded-none\",\n          \"w-full\",\n          font !== \"normal\" && \"retro\",\n          visualClasses\n        )}\n        variant={variant}\n      >\n        {children}\n      </ShadcnBadge>\n\n      {/* Left pixel bar */}\n      <div\n        className={cn(\n          \"-left-1.5 absolute inset-y-[4px] w-1.5\",\n          color,\n          visualClasses\n        )}\n      />\n      {/* Right pixel bar */}\n      <div\n        className={cn(\n          \"-right-1.5 absolute inset-y-[4px] w-1.5\",\n          color,\n          visualClasses\n        )}\n      />\n    </div>\n  );\n}\n\nexport { Badge };\n"}, {"path": "components/ui/8bit/card.tsx", "type": "registry:component", "content": "import { type VariantProps, cva } from \"class-variance-authority\";\n\nimport { cn } from \"@/lib/utils\";\n\nimport {\n  Card as ShadcnCard,\n  CardAction as ShadcnCardAction,\n  CardContent as ShadcnCardContent,\n  CardDescription as ShadcnCardDescription,\n  CardFooter as ShadcnCardFooter,\n  CardHeader as ShadcnCardHeader,\n  CardTitle as ShadcnCardTitle,\n} from \"@/components/ui/card\";\n\nimport \"@/components/ui/8bit/styles/retro.css\";\n\nexport const cardVariants = cva(\"\", {\n  variants: {\n    font: {\n      normal: \"\",\n      retro: \"retro\",\n    },\n  },\n  defaultVariants: {\n    font: \"retro\",\n  },\n});\n\nexport interface BitCardProps\n  extends React.ComponentProps<\"div\">,\n    VariantProps<typeof cardVariants> {\n  asChild?: boolean;\n}\n\nfunction Card({ className, font, ...props }: BitCardProps) {\n  return (\n    <div\n      className={cn(\n        \"relative bg-card text-card-foreground border-y-6 border-foreground dark:border-ring p-0!\",\n        className\n      )}\n    >\n      <ShadcnCard\n        {...props}\n        className={cn(\n          \"rounded-none border-0 w-full! h-full flex flex-col bg-card text-card-foreground shadow-none\",\n          font !== \"normal\" && \"retro\",\n          className\n        )}\n      />\n\n      <div\n        className={cn(\"absolute inset-0 border-x-6 -mx-1.5 border-inherit pointer-events-none\")}\n        aria-hidden=\"true\"\n      />\n    </div>\n  );\n}\n\nfunction CardHeader({ ...props }: BitCardProps) {\n  const { className, font } = props;\n\n  return (\n    <ShadcnCardHeader\n      className={cn(font !== \"normal\" && \"retro\", className)}\n      {...props}\n    />\n  );\n}\n\nfunction CardTitle({ ...props }: BitCardProps) {\n  const { className, font } = props;\n\n  return (\n    <ShadcnCardTitle\n      className={cn(font !== \"normal\" && \"retro\", className)}\n      {...props}\n    />\n  );\n}\n\nfunction CardDescription({ ...props }: BitCardProps) {\n  const { className, font } = props;\n\n  return (\n    <ShadcnCardDescription\n      className={cn(font !== \"normal\" && \"retro\", className)}\n      {...props}\n    />\n  );\n}\n\nfunction CardAction({ ...props }: BitCardProps) {\n  const { className, font } = props;\n\n  return (\n    <ShadcnCardAction\n      className={cn(font !== \"normal\" && \"retro\", className)}\n      {...props}\n    />\n  );\n}\n\nfunction CardContent({ ...props }: BitCardProps) {\n  const { className, font } = props;\n\n  return (\n    <ShadcnCardContent\n      className={cn(\"flex-1\", font !== \"normal\" && \"retro\", className)}\n      {...props}\n    />\n  );\n}\n\nfunction CardFooter({ ...props }: BitCardProps) {\n  const { className, font } = props;\n\n  return (\n    <ShadcnCardFooter\n      data-slot=\"card-footer\"\n      className={cn(font !== \"normal\" && \"retro\", className)}\n      {...props}\n    />\n  );\n}\n\nexport {\n  Card,\n  CardHeader,\n  CardFooter,\n  CardTitle,\n  CardAction,\n  CardDescription,\n  CardContent,\n};\n"}, {"path": "components/ui/8bit/carousel.tsx", "type": "registry:component", "content": "\"use client\";\n\nimport * as React from \"react\";\n\nimport useEmblaCarousel, {\n  type UseEmblaCarouselType,\n} from \"embla-carousel-react\";\n\nimport { cn } from \"@/lib/utils\";\n\nimport { Button } from \"@/components/ui/8bit/button\";\n\ntype CarouselApi = UseEmblaCarouselType[1];\ntype UseCarouselParameters = Parameters<typeof useEmblaCarousel>;\ntype CarouselOptions = UseCarouselParameters[0];\ntype CarouselPlugin = UseCarouselParameters[1];\n\ntype CarouselProps = {\n  opts?: CarouselOptions;\n  plugins?: CarouselPlugin;\n  orientation?: \"horizontal\" | \"vertical\";\n  setApi?: (api: CarouselApi) => void;\n};\n\ntype CarouselContextProps = {\n  carouselRef: ReturnType<typeof useEmblaCarousel>[0];\n  api: ReturnType<typeof useEmblaCarousel>[1];\n  scrollPrev: () => void;\n  scrollNext: () => void;\n  canScrollPrev: boolean;\n  canScrollNext: boolean;\n} & CarouselProps;\n\nconst CarouselContext = React.createContext<CarouselContextProps | null>(null);\n\nfunction useCarousel() {\n  const context = React.useContext(CarouselContext);\n\n  if (!context) {\n    throw new Error(\"useCarousel must be used within a <Carousel />\");\n  }\n\n  return context;\n}\n\nconst Carousel = React.forwardRef<\n  HTMLDivElement,\n  React.HTMLAttributes<HTMLDivElement> & CarouselProps\n>(\n  (\n    {\n      orientation = \"horizontal\",\n      opts,\n      setApi,\n      plugins,\n      className,\n      children,\n      ...props\n    },\n    ref\n  ) => {\n    const [carouselRef, api] = useEmblaCarousel(\n      {\n        ...opts,\n        axis: orientation === \"horizontal\" ? \"x\" : \"y\",\n      },\n      plugins\n    );\n    const [canScrollPrev, setCanScrollPrev] = React.useState(false);\n    const [canScrollNext, setCanScrollNext] = React.useState(false);\n\n    const onSelect = React.useCallback((api: CarouselApi) => {\n      if (!api) {\n        return;\n      }\n\n      setCanScrollPrev(api.canScrollPrev());\n      setCanScrollNext(api.canScrollNext());\n    }, []);\n\n    const scrollPrev = React.useCallback(() => {\n      console.log(\"scrolled prev\");\n      api?.scrollPrev();\n    }, [api]);\n\n    const scrollNext = React.useCallback(() => {\n      console.log(\"scrolled next\");\n      api?.scrollNext();\n    }, [api]);\n\n    const handleKeyDown = React.useCallback(\n      (event: React.KeyboardEvent<HTMLDivElement>) => {\n        if (event.key === \"ArrowLeft\") {\n          event.preventDefault();\n          scrollPrev();\n        } else if (event.key === \"ArrowRight\") {\n          event.preventDefault();\n          scrollNext();\n        }\n      },\n      [scrollPrev, scrollNext]\n    );\n\n    React.useEffect(() => {\n      if (!api || !setApi) {\n        return;\n      }\n\n      setApi(api);\n    }, [api, setApi]);\n\n    React.useEffect(() => {\n      if (!api) {\n        return;\n      }\n\n      onSelect(api);\n      api.on(\"reInit\", onSelect);\n      api.on(\"select\", onSelect);\n\n      return () => {\n        api?.off(\"select\", onSelect);\n      };\n    }, [api, onSelect]);\n\n    return (\n      <CarouselContext.Provider\n        value={{\n          carouselRef,\n          api: api,\n          opts,\n          orientation:\n            orientation || (opts?.axis === \"y\" ? \"vertical\" : \"horizontal\"),\n          scrollPrev,\n          scrollNext,\n          canScrollPrev,\n          canScrollNext,\n        }}\n      >\n        <div\n          ref={ref}\n          onKeyDownCapture={handleKeyDown}\n          className={cn(\"relative\", className)}\n          role=\"region\"\n          aria-roledescription=\"carousel\"\n          {...props}\n        >\n          {children}\n        </div>\n      </CarouselContext.Provider>\n    );\n  }\n);\nCarousel.displayName = \"Carousel\";\n\nconst CarouselContent = React.forwardRef<\n  HTMLDivElement,\n  React.HTMLAttributes<HTMLDivElement>\n>(({ className, ...props }, ref) => {\n  const { carouselRef, orientation } = useCarousel();\n\n  return (\n    <div ref={carouselRef} className=\"overflow-hidden\">\n      <div\n        ref={ref}\n        className={cn(\n          \"flex\",\n          orientation === \"horizontal\" ? \"-ml-4\" : \"-mt-4 flex-col\",\n          className\n        )}\n        {...props}\n      />\n    </div>\n  );\n});\nCarouselContent.displayName = \"CarouselContent\";\n\nconst CarouselItem = React.forwardRef<\n  HTMLDivElement,\n  React.HTMLAttributes<HTMLDivElement>\n>(({ className, ...props }, ref) => {\n  const { orientation } = useCarousel();\n\n  return (\n    <div\n      ref={ref}\n      role=\"group\"\n      aria-roledescription=\"slide\"\n      className={cn(\n        \"min-w-0 shrink-0 grow-0 basis-full\",\n        orientation === \"horizontal\" ? \"pl-4\" : \"pt-4\",\n        className\n      )}\n      {...props}\n    />\n  );\n});\nCarouselItem.displayName = \"CarouselItem\";\n\nconst CarouselPrevious = React.forwardRef<\n  HTMLButtonElement,\n  React.ComponentProps<typeof Button>\n>(({ className, variant = \"outline\", size = \"icon\", ...props }, ref) => {\n  const { orientation, scrollPrev, canScrollPrev } = useCarousel();\n\n  return (\n    <Button\n      ref={ref}\n      variant={variant}\n      size={size}\n      className={cn(\n        orientation === \"horizontal\"\n          ? \"top-1/2 -left-10 md:-left-14 -translate-y-1/2 active:-translate-y-1 w-8 h-9 md:w-9 md:h-10 \"\n          : \"-top-12 left-1/2 -translate-x-1/2 rotate-90 w-8 h-10 md:w-9 md:h-11\",\n        \"absolute rounded-none aspect-square grid place-items-center\",\n        className\n      )}\n      disabled={!canScrollPrev}\n      onClick={scrollPrev}\n      {...props}\n    >\n      <svg\n        width=\"50\"\n        height=\"50\"\n        viewBox=\"0 0 256 256\"\n        fill=\"currentColor\"\n        xmlns=\"http://www.w3.org/2000/svg\"\n        stroke=\"currentColor\"\n        strokeWidth=\"0.25\"\n        color=\"currentColor\"\n        aria-label=\"arrow-left\"\n      >\n        <rect x=\"64\" y=\"120\" width=\"14\" height=\"14\" rx=\"1\"></rect>\n        <rect x=\"96\" y=\"120\" width=\"14\" height=\"14\" rx=\"1\"></rect>\n        <rect x=\"80\" y=\"120\" width=\"14\" height=\"14\" rx=\"1\"></rect>\n        <rect x=\"112\" y=\"120\" width=\"14\" height=\"14\" rx=\"1\"></rect>\n        <rect x=\"144\" y=\"120\" width=\"14\" height=\"14\" rx=\"1\"></rect>\n        <rect x=\"160\" y=\"120\" width=\"14\" height=\"14\" rx=\"1\"></rect>\n        <rect x=\"80\" y=\"104\" width=\"14\" height=\"14\" rx=\"1\"></rect>\n        <rect x=\"96\" y=\"88\" width=\"14\" height=\"14\" rx=\"1\"></rect>\n        <rect x=\"112\" y=\"72\" width=\"14\" height=\"14\" rx=\"1\"></rect>\n        <rect x=\"80\" y=\"136\" width=\"14\" height=\"14\" rx=\"1\"></rect>\n        <rect x=\"96\" y=\"152\" width=\"14\" height=\"14\" rx=\"1\"></rect>\n        <rect x=\"112\" y=\"168\" width=\"14\" height=\"14\" rx=\"1\"></rect>\n        <rect x=\"176\" y=\"120\" width=\"14\" height=\"14\" rx=\"1\"></rect>\n        <rect x=\"128\" y=\"120\" width=\"14\" height=\"14\" rx=\"1\"></rect>\n      </svg>\n      <span className=\"sr-only\">Previous slide</span>\n    </Button>\n  );\n});\nCarouselPrevious.displayName = \"CarouselPrevious\";\n\nconst CarouselNext = React.forwardRef<\n  HTMLButtonElement,\n  React.ComponentProps<typeof Button>\n>(({ className, variant = \"outline\", size = \"icon\", ...props }, ref) => {\n  const { orientation, scrollNext, canScrollNext } = useCarousel();\n\n  return (\n    <Button\n      ref={ref}\n      variant={variant}\n      size={size}\n      className={cn(\n        orientation === \"horizontal\"\n          ? \"top-1/2 -right-10 md:-right-14 -translate-y-1/2 active:-translate-y-1 aspect-square shrink-0 w-8 h-9 md:w-9 md:h-10 \"\n          : \"-bottom-12 left-1/2 -translate-x-1/2 rotate-90 w-8 h-10 md:w-9 md:h-11\",\n        \"absolute rounded-none aspect-square grid place-items-center\",\n        className\n      )}\n      disabled={!canScrollNext}\n      onClick={scrollNext}\n      {...props}\n    >\n      <svg\n        width=\"50\"\n        height=\"50\"\n        viewBox=\"0 0 256 256\"\n        fill=\"currentColor\"\n        className=\"block\"\n        xmlns=\"http://www.w3.org/2000/svg\"\n        stroke=\"currentColor\"\n        strokeWidth=\"0.25\"\n        color=\"currentColor\"\n        aria-label=\"arrow-right\"\n      >\n        <rect x=\"64\" y=\"120\" width=\"14\" height=\"14\" rx=\"1\"></rect>\n        <rect x=\"96\" y=\"120\" width=\"14\" height=\"14\" rx=\"1\"></rect>\n        <rect x=\"80\" y=\"120\" width=\"14\" height=\"14\" rx=\"1\"></rect>\n        <rect x=\"112\" y=\"120\" width=\"14\" height=\"14\" rx=\"1\"></rect>\n        <rect x=\"144\" y=\"120\" width=\"14\" height=\"14\" rx=\"1\"></rect>\n        <rect x=\"160\" y=\"120\" width=\"14\" height=\"14\" rx=\"1\"></rect>\n        <rect x=\"160\" y=\"136\" width=\"14\" height=\"14\" rx=\"1\"></rect>\n        <rect x=\"144\" y=\"152\" width=\"14\" height=\"14\" rx=\"1\"></rect>\n        <rect x=\"128\" y=\"72\" width=\"14\" height=\"14\" rx=\"1\"></rect>\n        <rect x=\"128\" y=\"168\" width=\"14\" height=\"14\" rx=\"1\"></rect>\n        <rect x=\"176\" y=\"120\" width=\"14\" height=\"14\" rx=\"1\"></rect>\n        <rect x=\"160\" y=\"104\" width=\"14\" height=\"14\" rx=\"1\"></rect>\n        <rect x=\"144\" y=\"88\" width=\"14\" height=\"14\" rx=\"1\"></rect>\n        <rect x=\"128\" y=\"120\" width=\"14\" height=\"14\" rx=\"1\"></rect>\n      </svg>\n      <span className=\"sr-only\">Next slide</span>\n    </Button>\n  );\n});\nCarouselNext.displayName = \"CarouselNext\";\n\nexport {\n  type CarouselApi,\n  Carousel,\n  CarouselContent,\n  CarouselItem,\n  CarouselPrevious,\n  CarouselNext,\n};\n"}]}