{"$schema": "https://ui.shadcn.com/schema/registry-item.json", "name": "faq2", "type": "registry:block", "title": "8-bit FAQ2", "description": "Two-column card grid FAQ.", "categories": ["faq"], "registryDependencies": ["card"], "files": [{"path": "components/ui/8bit/blocks/faq2.tsx", "type": "registry:block", "target": "components/ui/8bit/blocks/faq2.tsx", "content": "import { cn } from \"@/lib/utils\";\n\nimport {\n  Card,\n  CardContent,\n  CardHeader,\n  CardTitle,\n} from \"@/components/ui/8bit/card\";\n\nimport \"@/components/ui/8bit/styles/retro.css\";\n\nexport interface FAQItem {\n  answer: string;\n  question: string;\n}\n\ninterface FAQ2Props {\n  className?: string;\n  description?: string;\n  items?: FAQItem[];\n  title?: string;\n}\n\nconst defaultItems: FAQItem[] = [\n  {\n    question: \"What do I get?\",\n    answer: \"50+ retro-styled components, blocks, and a full registry. Copy, paste, ship.\",\n  },\n  {\n    question: \"Is it free?\",\n    answer: \"The core library is 100% open source. Premium blocks and themes coming soon.\",\n  },\n  {\n    question: \"What frameworks?\",\n    answer: \"Built for React and Next.js. Works with any project that uses shadcn/ui.\",\n  },\n  {\n    question: \"How do I install?\",\n    answer: \"Run the shadcn CLI: pnpm dlx shadcn@latest add @8bitcn/button. That's it.\",\n  },\n  {\n    question: \"Can I customize?\",\n    answer: \"Everything is yours. Copy the source, change the colors, modify the borders. No lock-in.\",\n  },\n  {\n    question: \"Need help?\",\n    answer: \"Join our Discord or open a GitHub issue. The community is active and friendly.\",\n  },\n];\n\nexport default function FAQ2({\n  title = \"Quick Answers\",\n  description = \"No scrolling through walls of text\",\n  items = defaultItems,\n  className,\n}: FAQ2Props) {\n  return (\n    <section className={cn(\"w-full px-4 py-16\", className)}>\n      <div className=\"mx-auto max-w-4xl\">\n        {(title || description) && (\n          <div className=\"mb-10 text-center\">\n            {title && (\n              <h2 className=\"retro mb-3 font-bold text-2xl tracking-tight md:text-3xl\">\n                {title}\n              </h2>\n            )}\n            {description && (\n              <p className=\"retro mx-auto max-w-xl text-muted-foreground text-[9px]\">\n                {description}\n              </p>\n            )}\n          </div>\n        )}\n\n        <div className=\"grid gap-x-4 gap-y-1 sm:grid-cols-2\">\n          {items.map((item) => (\n            <Card key={item.question}>\n              <CardHeader className=\"pb-2\">\n                <CardTitle className=\"retro text-xs\">{item.question}</CardTitle>\n              </CardHeader>\n              <CardContent>\n                <p className=\"retro text-[9px] leading-relaxed text-muted-foreground\">\n                  {item.answer}\n                </p>\n              </CardContent>\n            </Card>\n          ))}\n        </div>\n      </div>\n    </section>\n  );\n}\n"}, {"path": "components/ui/8bit/styles/retro.css", "type": "registry:file", "target": "components/ui/8bit/styles/retro.css", "content": "@import url(\"https://fonts.googleapis.com/css2?family=Press+Start+2P&display=swap\");\n\n.retro {\n  font-family:\n    \"Press Start 2P\",\n    system-ui,\n    -apple-system,\n    sans-serif;\n  line-height: 1.5;\n  letter-spacing: 0.5px;\n}\n\n.pixelated {\n  image-rendering: pixelated;\n  image-rendering: crisp-edges;\n}"}, {"path": "components/ui/8bit/card.tsx", "type": "registry:component", "content": "import { type VariantProps, cva } from \"class-variance-authority\";\n\nimport { cn } from \"@/lib/utils\";\n\nimport {\n  Card as ShadcnCard,\n  CardAction as ShadcnCardAction,\n  CardContent as ShadcnCardContent,\n  CardDescription as ShadcnCardDescription,\n  CardFooter as ShadcnCardFooter,\n  CardHeader as ShadcnCardHeader,\n  CardTitle as ShadcnCardTitle,\n} from \"@/components/ui/card\";\n\nimport \"@/components/ui/8bit/styles/retro.css\";\n\nexport const cardVariants = cva(\"\", {\n  variants: {\n    font: {\n      normal: \"\",\n      retro: \"retro\",\n    },\n  },\n  defaultVariants: {\n    font: \"retro\",\n  },\n});\n\nexport interface BitCardProps\n  extends React.ComponentProps<\"div\">,\n    VariantProps<typeof cardVariants> {\n  asChild?: boolean;\n}\n\nfunction Card({ className, font, ...props }: BitCardProps) {\n  return (\n    <div\n      className={cn(\n        \"relative bg-card text-card-foreground border-y-6 border-foreground dark:border-ring p-0!\",\n        className\n      )}\n    >\n      <ShadcnCard\n        {...props}\n        className={cn(\n          \"rounded-none border-0 w-full! h-full flex flex-col bg-card text-card-foreground shadow-none\",\n          font !== \"normal\" && \"retro\",\n          className\n        )}\n      />\n\n      <div\n        className={cn(\"absolute inset-0 border-x-6 -mx-1.5 border-inherit pointer-events-none\")}\n        aria-hidden=\"true\"\n      />\n    </div>\n  );\n}\n\nfunction CardHeader({ ...props }: BitCardProps) {\n  const { className, font } = props;\n\n  return (\n    <ShadcnCardHeader\n      className={cn(font !== \"normal\" && \"retro\", className)}\n      {...props}\n    />\n  );\n}\n\nfunction CardTitle({ ...props }: BitCardProps) {\n  const { className, font } = props;\n\n  return (\n    <ShadcnCardTitle\n      className={cn(font !== \"normal\" && \"retro\", className)}\n      {...props}\n    />\n  );\n}\n\nfunction CardDescription({ ...props }: BitCardProps) {\n  const { className, font } = props;\n\n  return (\n    <ShadcnCardDescription\n      className={cn(font !== \"normal\" && \"retro\", className)}\n      {...props}\n    />\n  );\n}\n\nfunction CardAction({ ...props }: BitCardProps) {\n  const { className, font } = props;\n\n  return (\n    <ShadcnCardAction\n      className={cn(font !== \"normal\" && \"retro\", className)}\n      {...props}\n    />\n  );\n}\n\nfunction CardContent({ ...props }: BitCardProps) {\n  const { className, font } = props;\n\n  return (\n    <ShadcnCardContent\n      className={cn(\"flex-1\", font !== \"normal\" && \"retro\", className)}\n      {...props}\n    />\n  );\n}\n\nfunction CardFooter({ ...props }: BitCardProps) {\n  const { className, font } = props;\n\n  return (\n    <ShadcnCardFooter\n      data-slot=\"card-footer\"\n      className={cn(font !== \"normal\" && \"retro\", className)}\n      {...props}\n    />\n  );\n}\n\nexport {\n  Card,\n  CardHeader,\n  CardFooter,\n  CardTitle,\n  CardAction,\n  CardDescription,\n  CardContent,\n};\n"}]}