{"$schema": "https://ui.shadcn.com/schema/registry-item.json", "name": "sheet7", "type": "registry:component", "title": "Sheet", "description": "Sheet built with shadcn/ui.", "dependencies": ["class-variance-authority", "radix-ui", "lucide-react"], "files": [{"path": "contents/components/sheet/7/index.tsx", "content": "\"use client\";\n\nimport { Button } from \"@/components/ui/button\";\nimport { Input } from \"@/components/ui/input\";\nimport { Label } from \"@/components/ui/label\";\nimport { Avatar, AvatarFallback, AvatarImage } from \"@/components/ui/avatar\";\nimport {\n  Sheet,\n  SheetContent,\n  SheetFooter,\n  SheetHeader,\n  SheetTitle,\n  SheetTrigger\n} from \"@/components/ui/sheet\";\n\nexport default function SheetComponent() {\n  return (\n    <Sheet>\n      <SheetTrigger asChild>\n        <Button variant=\"outline\">Edit Profile</Button>\n      </SheetTrigger>\n      <SheetContent className=\"overflow-y-auto\">\n        <SheetHeader>\n          <SheetTitle>Edit Profile</SheetTitle>\n        </SheetHeader>\n        <div className=\"space-y-6 px-4\">\n          <div className=\"flex items-center gap-4\">\n            <Avatar className=\"size-16\">\n              <AvatarImage src=\"https://i.pravatar.cc/150?img=12\" alt=\"Profile\" />\n              <AvatarFallback>JD</AvatarFallback>\n            </Avatar>\n            <Button variant=\"link\" className=\"text-primary h-auto p-0\">\n              Change Picture\n            </Button>\n          </div>\n\n          <div className=\"space-y-4\">\n            <div className=\"space-y-2\">\n              <Label htmlFor=\"name\">Name</Label>\n              <Input id=\"name\" defaultValue=\"John Doe\" />\n            </div>\n\n            <div className=\"space-y-2\">\n              <Label htmlFor=\"email\">Email</Label>\n              <Input id=\"email\" type=\"email\" defaultValue=\"sales@andromedia.co.id\" />\n            </div>\n\n            <div className=\"space-y-2\">\n              <Label htmlFor=\"phone\">Phone Number</Label>\n              <Input id=\"phone\" type=\"tel\" defaultValue=\"+6289612311111\" />\n            </div>\n\n            <div className=\"space-y-2\">\n              <Label htmlFor=\"password\">Password</Label>\n              <Input id=\"password\" type=\"password\" defaultValue=\"************\" />\n            </div>\n\n            <div className=\"space-y-2\">\n              <Label htmlFor=\"retype-password\">Retype Password</Label>\n              <Input id=\"retype-password\" type=\"password\" defaultValue=\"************\" />\n            </div>\n          </div>\n        </div>\n\n        <SheetFooter className=\"flex gap-3 px-4\">\n          <Button>Save</Button>\n        </SheetFooter>\n      </SheetContent>\n    </Sheet>\n  );\n}\n", "type": "registry:component", "target": "components/sheet7.tsx"}, {"path": "components/ui/button.tsx", "content": "import * as React from \"react\"\nimport { cva, type VariantProps } from \"class-variance-authority\"\nimport { Slot } from \"radix-ui\"\n\nimport { cn } from \"@/lib/utils\"\n\nconst buttonVariants = cva(\n  \"inline-flex shrink-0 items-center justify-center gap-2 rounded-md text-sm font-medium whitespace-nowrap transition-all outline-none focus-visible:border-ring focus-visible:ring-[3px] focus-visible:ring-ring/50 disabled:pointer-events-none disabled:opacity-50 aria-invalid:border-destructive aria-invalid:ring-destructive/20 dark:aria-invalid:ring-destructive/40 [&_svg]:pointer-events-none [&_svg]:shrink-0 [&_svg:not([class*='size-'])]:size-4\",\n  {\n    variants: {\n      variant: {\n        default: \"bg-primary text-primary-foreground hover:bg-primary/90\",\n        destructive:\n          \"bg-destructive text-white hover:bg-destructive/90 focus-visible:ring-destructive/20 dark:bg-destructive/60 dark:focus-visible:ring-destructive/40\",\n        outline:\n          \"border bg-background shadow-xs hover:bg-accent hover:text-accent-foreground dark:border-input dark:bg-input/30 dark:hover:bg-input/50\",\n        secondary:\n          \"bg-secondary text-secondary-foreground hover:bg-secondary/80\",\n        ghost:\n          \"hover:bg-accent hover:text-accent-foreground dark:hover:bg-accent/50\",\n        link: \"text-primary underline-offset-4 hover:underline\",\n      },\n      size: {\n        default: \"h-9 px-4 py-2 has-[>svg]:px-3\",\n        xs: \"h-6 gap-1 rounded-md px-2 text-xs has-[>svg]:px-1.5 [&_svg:not([class*='size-'])]:size-3\",\n        sm: \"h-8 gap-1.5 rounded-md px-3 has-[>svg]:px-2.5\",\n        lg: \"h-10 rounded-md px-6 has-[>svg]:px-4\",\n        icon: \"size-9\",\n        \"icon-xs\": \"size-6 rounded-md [&_svg:not([class*='size-'])]:size-3\",\n        \"icon-sm\": \"size-8\",\n        \"icon-lg\": \"size-10\",\n      },\n    },\n    defaultVariants: {\n      variant: \"default\",\n      size: \"default\",\n    },\n  }\n)\n\nfunction Button({\n  className,\n  variant = \"default\",\n  size = \"default\",\n  asChild = false,\n  ...props\n}: React.ComponentProps<\"button\"> &\n  VariantProps<typeof buttonVariants> & {\n    asChild?: boolean\n  }) {\n  const Comp = asChild ? Slot.Root : \"button\"\n\n  return (\n    <Comp\n      data-slot=\"button\"\n      data-variant={variant}\n      data-size={size}\n      className={cn(buttonVariants({ variant, size, className }))}\n      {...props}\n    />\n  )\n}\n\nexport { Button, buttonVariants }\n", "type": "registry:ui", "target": ""}, {"path": "components/ui/input.tsx", "content": "import * as React from \"react\";\n\nimport { cn } from \"@/lib/utils\";\n\nfunction Input({ className, type, ...props }: React.ComponentProps<\"input\">) {\n  return (\n    <input\n      type={type}\n      data-slot=\"input\"\n      className={cn(\n        \"file:text-foreground placeholder:text-muted-foreground selection:bg-primary selection:text-primary-foreground dark:bg-input/30 border-input h-9 w-full min-w-0 rounded-md border bg-transparent px-3 py-1 text-base shadow-xs transition-[color,box-shadow] outline-none file:inline-flex file:h-7 file:border-0 file:bg-transparent file:text-sm file:font-medium disabled:pointer-events-none disabled:cursor-not-allowed disabled:opacity-50 md:text-sm\",\n        \"focus-visible:border-ring focus-visible:ring-ring/50 focus-visible:ring-[3px]\",\n        \"aria-invalid:ring-destructive/20 dark:aria-invalid:ring-destructive/40 aria-invalid:border-destructive\",\n        className,\n      )}\n      {...props}\n    />\n  );\n}\n\nexport { Input };\n", "type": "registry:ui", "target": ""}, {"path": "components/ui/label.tsx", "content": "\"use client\"\n\nimport * as React from \"react\"\nimport { Label as LabelPrimitive } from \"radix-ui\"\n\nimport { cn } from \"@/lib/utils\"\n\nfunction Label({\n  className,\n  ...props\n}: React.ComponentProps<typeof LabelPrimitive.Root>) {\n  return (\n    <LabelPrimitive.Root\n      data-slot=\"label\"\n      className={cn(\n        \"flex items-center gap-2 text-sm leading-none font-medium select-none group-data-[disabled=true]:pointer-events-none group-data-[disabled=true]:opacity-50 peer-disabled:cursor-not-allowed peer-disabled:opacity-50\",\n        className\n      )}\n      {...props}\n    />\n  )\n}\n\nexport { Label }\n", "type": "registry:ui", "target": ""}, {"path": "components/ui/avatar.tsx", "content": "\"use client\"\n\nimport * as React from \"react\"\nimport { Avatar as AvatarPrimitive } from \"radix-ui\"\n\nimport { cn } from \"@/lib/utils\"\n\nfunction Avatar({\n  className,\n  ...props\n}: React.ComponentProps<typeof AvatarPrimitive.Root>) {\n  return (\n    <AvatarPrimitive.Root\n      data-slot=\"avatar\"\n      className={cn(\n        \"relative flex size-8 shrink-0 overflow-hidden rounded-full\",\n        className\n      )}\n      {...props}\n    />\n  )\n}\n\nfunction AvatarImage({\n  className,\n  ...props\n}: React.ComponentProps<typeof AvatarPrimitive.Image>) {\n  return (\n    <AvatarPrimitive.Image\n      data-slot=\"avatar-image\"\n      className={cn(\"aspect-square size-full\", className)}\n      {...props}\n    />\n  )\n}\n\nfunction AvatarFallback({\n  className,\n  ...props\n}: React.ComponentProps<typeof AvatarPrimitive.Fallback>) {\n  return (\n    <AvatarPrimitive.Fallback\n      data-slot=\"avatar-fallback\"\n      className={cn(\n        \"bg-muted flex size-full items-center justify-center rounded-full\",\n        className\n      )}\n      {...props}\n    />\n  )\n}\n\nexport { Avatar, AvatarImage, AvatarFallback }\n", "type": "registry:ui", "target": ""}, {"path": "components/ui/sheet.tsx", "content": "\"use client\"\n\nimport * as React from \"react\"\nimport { Dialog as SheetPrimitive } from \"radix-ui\"\nimport { XIcon } from \"lucide-react\"\n\nimport { cn } from \"@/lib/utils\"\n\nfunction Sheet({ ...props }: React.ComponentProps<typeof SheetPrimitive.Root>) {\n  return <SheetPrimitive.Root data-slot=\"sheet\" {...props} />\n}\n\nfunction SheetTrigger({\n  ...props\n}: React.ComponentProps<typeof SheetPrimitive.Trigger>) {\n  return <SheetPrimitive.Trigger data-slot=\"sheet-trigger\" {...props} />\n}\n\nfunction SheetClose({\n  ...props\n}: React.ComponentProps<typeof SheetPrimitive.Close>) {\n  return <SheetPrimitive.Close data-slot=\"sheet-close\" {...props} />\n}\n\nfunction SheetPortal({\n  ...props\n}: React.ComponentProps<typeof SheetPrimitive.Portal>) {\n  return <SheetPrimitive.Portal data-slot=\"sheet-portal\" {...props} />\n}\n\nfunction SheetOverlay({\n  className,\n  ...props\n}: React.ComponentProps<typeof SheetPrimitive.Overlay>) {\n  return (\n    <SheetPrimitive.Overlay\n      data-slot=\"sheet-overlay\"\n      className={cn(\n        \"data-[state=open]:animate-in data-[state=closed]:animate-out data-[state=closed]:fade-out-0 data-[state=open]:fade-in-0 fixed inset-0 z-50 bg-black/50\",\n        className\n      )}\n      {...props}\n    />\n  )\n}\n\nfunction SheetContent({\n  className,\n  children,\n  side = \"right\",\n  ...props\n}: React.ComponentProps<typeof SheetPrimitive.Content> & {\n  side?: \"top\" | \"right\" | \"bottom\" | \"left\"\n}) {\n  return (\n    <SheetPortal>\n      <SheetOverlay />\n      <SheetPrimitive.Content\n        data-slot=\"sheet-content\"\n        className={cn(\n          \"bg-background data-[state=open]:animate-in data-[state=closed]:animate-out fixed z-50 flex flex-col gap-4 shadow-lg transition ease-in-out data-[state=closed]:duration-300 data-[state=open]:duration-500\",\n          side === \"right\" &&\n            \"data-[state=closed]:slide-out-to-right data-[state=open]:slide-in-from-right inset-y-0 right-0 h-full w-3/4 border-l sm:max-w-sm\",\n          side === \"left\" &&\n            \"data-[state=closed]:slide-out-to-left data-[state=open]:slide-in-from-left inset-y-0 left-0 h-full w-3/4 border-r sm:max-w-sm\",\n          side === \"top\" &&\n            \"data-[state=closed]:slide-out-to-top data-[state=open]:slide-in-from-top inset-x-0 top-0 h-auto border-b\",\n          side === \"bottom\" &&\n            \"data-[state=closed]:slide-out-to-bottom data-[state=open]:slide-in-from-bottom inset-x-0 bottom-0 h-auto border-t\",\n          className\n        )}\n        {...props}\n      >\n        {children}\n        <SheetPrimitive.Close className=\"ring-offset-background focus:ring-ring data-[state=open]:bg-secondary absolute top-4 right-4 rounded-xs opacity-70 transition-opacity hover:opacity-100 focus:ring-2 focus:ring-offset-2 focus:outline-hidden disabled:pointer-events-none\">\n          <XIcon className=\"size-4\" />\n          <span className=\"sr-only\">Close</span>\n        </SheetPrimitive.Close>\n      </SheetPrimitive.Content>\n    </SheetPortal>\n  )\n}\n\nfunction SheetHeader({ className, ...props }: React.ComponentProps<\"div\">) {\n  return (\n    <div\n      data-slot=\"sheet-header\"\n      className={cn(\"flex flex-col gap-1.5 p-4\", className)}\n      {...props}\n    />\n  )\n}\n\nfunction SheetFooter({ className, ...props }: React.ComponentProps<\"div\">) {\n  return (\n    <div\n      data-slot=\"sheet-footer\"\n      className={cn(\"mt-auto flex flex-col gap-2 p-4\", className)}\n      {...props}\n    />\n  )\n}\n\nfunction SheetTitle({\n  className,\n  ...props\n}: React.ComponentProps<typeof SheetPrimitive.Title>) {\n  return (\n    <SheetPrimitive.Title\n      data-slot=\"sheet-title\"\n      className={cn(\"text-foreground font-semibold\", className)}\n      {...props}\n    />\n  )\n}\n\nfunction SheetDescription({\n  className,\n  ...props\n}: React.ComponentProps<typeof SheetPrimitive.Description>) {\n  return (\n    <SheetPrimitive.Description\n      data-slot=\"sheet-description\"\n      className={cn(\"text-muted-foreground text-sm\", className)}\n      {...props}\n    />\n  )\n}\n\nexport {\n  Sheet,\n  SheetTrigger,\n  SheetClose,\n  SheetContent,\n  SheetHeader,\n  SheetFooter,\n  SheetTitle,\n  SheetDescription,\n}\n", "type": "registry:ui", "target": ""}]}