{"$schema": "https://ui.shadcn.com/schema/registry-item.json", "extends": "none", "name": "breadcrumbs-separator-example", "title": "Breadcrumbs Separator", "description": "breadcrumbs-separator-example", "registryDependencies": ["https://intentui.com/r/breadcrumbs"], "files": [{"path": "src/components/examples/navigation/breadcrumbs/breadcrumbs-separator-example.tsx", "content": "\"use client\"\n\nimport { Breadcrumbs, BreadcrumbsItem } from \"@/components/ui/breadcrumbs\"\n\nexport default function BreadcrumbsSeparatorDemo() {\n  return (\n    <Breadcrumbs separator=\"slash\">\n      <BreadcrumbsItem separator=\"slash\" href=\"#\">\n        Home\n      </BreadcrumbsItem>\n      <BreadcrumbsItem href=\"#\">Design System</BreadcrumbsItem>\n      <BreadcrumbsItem>Collections</BreadcrumbsItem>\n    </Breadcrumbs>\n  )\n}\n", "type": "registry:page", "target": "app/breadcrumbs-separator-example/page.tsx"}], "type": "registry:page"}